{
"type": "FeatureCollection",
"name": "newpoint",
"crs": { "type": "name", "properties": { "name": "urn:ogc:def:crs:OGC:1.3:CRS84" } },
"features": [
{ "type": "Feature", "properties": { "id": 1 }, "geometry": { "type": "Point", "coordinates": [ -79.051233670007647, 35.912060116879786 ] } }
]
}
